odoo/addons/iot_input_oca/README.rst
odoo/addons/iot_input_oca/__init__.py
odoo/addons/iot_input_oca/__manifest__.py
odoo/addons/iot_input_oca/controller/__init__.py
odoo/addons/iot_input_oca/controller/iot_input_controller.py
odoo/addons/iot_input_oca/examples/multi_input_values.json
odoo/addons/iot_input_oca/i18n/ca.po
odoo/addons/iot_input_oca/i18n/es.po
odoo/addons/iot_input_oca/i18n/fa.po
odoo/addons/iot_input_oca/i18n/iot_input.pot
odoo/addons/iot_input_oca/i18n/iot_input_oca.pot
odoo/addons/iot_input_oca/i18n/it.po
odoo/addons/iot_input_oca/models/__init__.py
odoo/addons/iot_input_oca/models/iot_device.py
odoo/addons/iot_input_oca/models/iot_device_input.py
odoo/addons/iot_input_oca/readme/CONTRIBUTORS.md
odoo/addons/iot_input_oca/readme/DESCRIPTION.md
odoo/addons/iot_input_oca/readme/USAGE.md
odoo/addons/iot_input_oca/security/ir.model.access.csv
odoo/addons/iot_input_oca/static/description/icon.png
odoo/addons/iot_input_oca/static/description/index.html
odoo/addons/iot_input_oca/tests/__init__.py
odoo/addons/iot_input_oca/tests/models.py
odoo/addons/iot_input_oca/tests/test_iot_controller.py
odoo/addons/iot_input_oca/tests/test_iot_in.py
odoo/addons/iot_input_oca/tests/test_iot_multi_input.py
odoo/addons/iot_input_oca/views/iot_device_input_views.xml
odoo/addons/iot_input_oca/views/iot_device_views.xml
odoo_addon_iot_input_oca-17.0.1.0.0.4.dist-info/METADATA
odoo_addon_iot_input_oca-17.0.1.0.0.4.dist-info/WHEEL
odoo_addon_iot_input_oca-17.0.1.0.0.4.dist-info/top_level.txt
odoo_addon_iot_input_oca-17.0.1.0.0.4.dist-info/RECORD
