Metadata-Version: 2.1
Name: odoo-addon-iot_input_oca
Version: 17.0.1.0.0.4
Requires-Python: >=3.10
Requires-Dist: odoo-addon-iot_oca>=17.0dev,<17.1dev
Requires-Dist: odoo>=17.0a,<17.1dev
Summary: IoT Input module
Home-page: https://github.com/OCA/iot
License: AGPL-3
Author: Creu Blanca, Odoo Community Association (OCA)
Author-email: support@odoo-community.org
Classifier: Programming Language :: Python
Classifier: Framework :: Odoo
Classifier: Framework :: Odoo :: 17.0
Classifier: License :: OSI Approved :: GNU Affero General Public License v3
